ModernRelay/__init__.py
ModernRelay/__main__.py
ModernRelay/agents.py
ModernRelay/auth.py
ModernRelay/common.py
ModernRelay/config.yaml
ModernRelay/exceptions.py
ModernRelay/file_manager.py
ModernRelay/modern_relay.py
ModernRelay/relay.py
ModernRelay/tests/__init__.py
ModernRelay/tests/conftest.py
ModernRelay/tests/test_agents.py
ModernRelay/tests/test_auth.py
ModernRelay/tests/test_file_manager.py
ModernRelay/tests/test_relay.py
ModernRelay/tests/test_files/bad-spooled-email-decode-error
ModernRelay/tests/test_files/bad-spooled-email-no-peer
ModernRelay/tests/test_files/good-spooled-email-172-16-128-109
ModernRelay/tests/test_files/good-spooled-email-172-16-129-109
ModernRelay/tests/test_files/good-spooled-email-172-16-130-109
ModernRelay/tests/test_files/test.db
ModernRelay-0.0.3.dist-info/LICENSE
ModernRelay-0.0.3.dist-info/WHEEL
ModernRelay-0.0.3.dist-info/METADATA
ModernRelay-0.0.3.dist-info/RECORD
