Metadata-Version: 2.1
Name: ModernRelay
Version: 0.0.3
Summary: An asynchronous, highly configurable SMTP relay
Home-page: https://github.com/blbuford/ModernRelay
Author: Brett Buford
Author-email: blbuford@gmail.com
Requires-Python: >=3.6
Classifier: Development Status :: 4 - Beta
Classifier: Environment :: Console
Classifier: Intended Audience :: Developers
Classifier: Intended Audience :: Information Technology
Classifier: Natural Language :: English
Classifier: License :: OSI Approved :: MIT License
Classifier: Programming Language :: Python
Classifier: Programming Language :: Python :: 3
Classifier: Programming Language :: Python :: 3.6
Classifier: Programming Language :: Python :: 3.7
Classifier: Programming Language :: Python :: 3.8
Classifier: Programming Language :: Python :: 3.9
Classifier: Programming Language :: Python :: 3.10
Classifier: Programming Language :: Python :: Implementation :: CPython
Classifier: Programming Language :: Python :: Implementation :: PyPy
Classifier: Topic :: Communications :: Email
Requires-Dist: aiofiles
Requires-Dist: aiohttp
Requires-Dist: aiosmtpd
Requires-Dist: APScheduler
Requires-Dist: argon2-cffi
Requires-Dist: confuse
Requires-Dist: msgraph-async
Requires-Dist: check-manifest ; extra == "dev"
Requires-Dist: python-dotenv ; extra == "dev"
Requires-Dist: sphinx ; extra == "doc"
Requires-Dist: sphinx_RTD_theme ; extra == "doc"
Requires-Dist: asynctest ; extra == "test"
Requires-Dist: coverage ; extra == "test"
Requires-Dist: flake8 ; extra == "test"
Requires-Dist: pytest ; extra == "test"
Requires-Dist: pytest-asyncio ; extra == "test"
Requires-Dist: pytest-cov ; extra == "test"
Requires-Dist: pytest-sugar ; extra == "test"
Requires-Dist: tox ; extra == "test"
Provides-Extra: dev
Provides-Extra: doc
Provides-Extra: test
